solarwolf/__init__.py
solarwolf/__main__.py
solarwolf/allmodules.py
solarwolf/cli.py
solarwolf/errorbox.py
solarwolf/game.py
solarwolf/gamecreds.py
solarwolf/gamefinish.py
solarwolf/gamehelp.py
solarwolf/gameinit.py
solarwolf/gamemenu.py
solarwolf/gamename.py
solarwolf/gamenews.py
solarwolf/gamepause.py
solarwolf/gameplay.py
solarwolf/gamepref.py
solarwolf/gamesetup.py
solarwolf/gamestart.py
solarwolf/gamewin.py
solarwolf/gfx.py
solarwolf/hud.py
solarwolf/input.py
solarwolf/levels.py
solarwolf/main.py
solarwolf/objasteroid.py
solarwolf/objbox.py
solarwolf/objexplode.py
solarwolf/objguard.py
solarwolf/objlaser.py
solarwolf/objpopshot.py
solarwolf/objpowerup.py
solarwolf/objship.py
solarwolf/objshot.py
solarwolf/objsmoke.py
solarwolf/objtele.py
solarwolf/objtext.py
solarwolf/objwarp.py
solarwolf/players.py
solarwolf/score.py
solarwolf/snd.py
solarwolf/stars.py
solarwolf/txt.py
solarwolf/data/asteroid.png
solarwolf/data/baddie-teleport.png
solarwolf/data/baddie.png
solarwolf/data/bigboxes.png
solarwolf/data/bonus-bullet.png
solarwolf/data/bonus-shield.png
solarwolf/data/boxes.png
solarwolf/data/btn-add.gif
solarwolf/data/btn-delete.gif
solarwolf/data/debris-base.png
solarwolf/data/debris-bubble.png
solarwolf/data/debris-motor.png
solarwolf/data/debris1.png
solarwolf/data/debris2.png
solarwolf/data/debris3.png
solarwolf/data/debris4.png
solarwolf/data/downerror.gif
solarwolf/data/download.png
solarwolf/data/downok.gif
solarwolf/data/end.gif
solarwolf/data/explosion.png
solarwolf/data/fame.png
solarwolf/data/fire.png
solarwolf/data/hud.gif
solarwolf/data/hud2.gif
solarwolf/data/levels.txt
solarwolf/data/logo.png
solarwolf/data/menu_creds_off.png
solarwolf/data/menu_creds_on.png
solarwolf/data/menu_news_off.png
solarwolf/data/menu_news_on.png
solarwolf/data/menu_on_bgd.png
solarwolf/data/menu_quit_off.png
solarwolf/data/menu_quit_on.png
solarwolf/data/menu_setup_off.png
solarwolf/data/menu_setup_on.png
solarwolf/data/menu_start_off.png
solarwolf/data/menu_start_on.png
solarwolf-1.6.0.dev7.dist-info/METADATA
solarwolf-1.6.0.dev7.dist-info/WHEEL
solarwolf-1.6.0.dev7.dist-info/entry_points.txt
solarwolf-1.6.0.dev7.dist-info/top_level.txt
solarwolf-1.6.0.dev7.dist-info/RECORD
